tartape/__init__.py
tartape/constants.py
tartape/core.py
tartape/enums.py
tartape/inventory.py
tartape/schemas.py
tartape-1.6.0.dist-info/METADATA
tartape-1.6.0.dist-info/WHEEL
tartape-1.6.0.dist-info/top_level.txt
tartape-1.6.0.dist-info/RECORD
