Metadata-Version: 2.4
Name: tartape
Version: 1.6.0
Summary: An efficient, secure, and deterministic TAR streaming engine.
Home-page: https://github.com/CalumRakk/tartape
Author: Leo
Author-email: leocasti2@gmail.com
Keywords: tar,streaming,deterministic,resumable,cloud-backup,storage
Classifier: Programming Language :: Python :: 3
Classifier: Programming Language :: Python :: 3.10
Classifier: Programming Language :: Python :: 3.11
Classifier: Programming Language :: Python :: 3.12
Classifier: License :: OSI Approved :: MIT License
Classifier: Operating System :: OS Independent
Classifier: Topic :: System :: Archiving
Classifier: Intended Audience :: Developers
Requires-Python: >=3.10.0
Requires-Dist: pydantic>=2.11.7
Dynamic: author
Dynamic: author-email
Dynamic: classifier
Dynamic: description
Dynamic: description-content-type
Dynamic: home-page
Dynamic: keywords
Dynamic: requires-dist
Dynamic: requires-python
Dynamic: summary
